{"HISTORY": {"par": ["STROKEVOLUME"], "nei": []}, "CVP": {"par": [], "nei": []}, "PCWP": {"par": [], "nei": []}, "HYPOVOLEMIA": {"par": ["PCWP"], "nei": []}, "LVEDVOLUME": {"par": [], "nei": []}, "LVFAILURE": {"par": [], "nei": []}, "STROKEVOLUME": {"par": ["HYPOVOLEMIA"], "nei": []}, "ERRLOWOUTPUT": {"par": [], "nei": []}, "HRBP": {"par": [], "nei": []}, "HREKG": {"par": ["HR", "ERRCAUTER"], "nei": []}, "ERRCAUTER": {"par": [], "nei": []}, "HRSAT": {"par": ["HREKG", "ERRCAUTER"], "nei": []}, "INSUFFANESTH": {"par": ["LVFAILURE"], "nei": []}, "ANAPHYLAXIS": {"par": [], "nei": []}, "TPR": {"par": [], "nei": []}, "EXPCO2": {"par": [], "nei": []}, "KINKEDTUBE": {"par": [], "nei": []}, "MINVOL": {"par": [], "nei": []}, "FIO2": {"par": [], "nei": []}, "PVSAT": {"par": [], "nei": []}, "SAO2": {"par": [], "nei": []}, "PAP": {"par": [], "nei": []}, "PULMEMBOLUS": {"par": ["ANAPHYLAXIS"], "nei": []}, "SHUNT": {"par": [], "nei": []}, "INTUBATION": {"par": ["SHUNT"], "nei": []}, "PRESS": {"par": [], "nei": []}, "DISCONNECT": {"par": ["ARTCO2"], "nei": []}, "MINVOLSET": {"par": ["ARTCO2"], "nei": []}, "VENTMACH": {"par": [], "nei": []}, "VENTTUBE": {"par": [], "nei": []}, "VENTLUNG": {"par": [], "nei": []}, "VENTALV": {"par": [], "nei": []}, "ARTCO2": {"par": ["PVSAT"], "nei": []}, "CATECHOL": {"par": [], "nei": []}, "HR": {"par": ["HRBP"], "nei": []}, "CO": {"par": [], "nei": []}, "BP": {"par": [], "nei": []}}